Workbook
Name aaaaaa: #REF!
Name amarks: #REF!
Name cost: [1]Sheet22!$D$4
Name cost: [2]Sheet22!$D$4
Name criteria1: '[3]Advance filter'!#REF!
Name Employee_ID: "sheet34!a1:a10"
Name etype: '[4]Data validation'!$G$29:$G$31
Name etype: '[4]Data validation'!$G$29:$G$31
Name etype: '[5]Data validation'!$G$29:$G$31
Name GST: #REF!
Name GST: #REF!
Name GST: '[7]relative and absolute reference'!$D$1
Name lap_price: #REF!
Name lap_price: #REF!
Name lap_price: #REF!
Name lap_price: #REF!
Name lap_price2: #REF!
Name lap_qty: #REF!
Name lap_qty: #REF!
Name lap_qty: #REF!
Name lap_qty: #REF!
Name laptop_price: #REF!
Name Laptop_qty: #REF!
Name laptopprice: #REF!
Name marks_list: #REF!
Name marks_list: #REF!
Name marks_list: #REF!
Name marks_list1: #REF!
Name markslist: #REF!
Name mobileprice: #REF!
Name mobileprice: #REF!
Name mobileprice: '[7]relative and absolute reference'!$C$4:$C$8
Name PF: [8]Sheet15!$B$3
Name PF: [8]Sheet15!$B$3
Name PF: [7]Sheet15!$B$3
Name Price: #REF!
Name Price: #REF!
Name Price: '[7]relative and absolute reference'!$C$38
Name qty: [1]Sheet22!$D$5
Name qty: [2]Sheet22!$D$5
Name quantity: #REF!
Name quantity: #REF!
Name quantity: '[7]relative and absolute reference'!$C$39
Name salary: [1]Sheet22!$F$2:$F$6
Name salary: [2]Sheet22!$F$2:$F$6
Name salesvalue: [9]Sheet25!$E$3:$E$10
Name totaltax: #REF!
Name totaltax: #REF!
Name totaltax: '[7]relative and absolute reference'!$D$4:$D$8

Sheet Formula audting
A1: SL No | B1: Student Name | C1: Written test | D1: Interview | E1: Practicals | F1: Total | G1: Average | H1: Rounded
A2: 1 | B2: Avinash | C2: 95 | D2: 48 | E2: 45 | F2: =SUM(C2:E2) -> 188 | G2: =ROUND(AVERAGE(C2:E2),2) -> 62.67 | H2: =ROUND(G2,2) -> 62.67
A3: 2 | B3: Mahadev | C3: 25 | D3: 45 | E3: 85 | F3: =SUM(C3:E3) -> 155 | G3: =AVERAGE(C3:E3) -> 51.666667 | H3: =ROUND(G3,2) -> 51.67
A4: 3 | B4: Manoj | C4: 97 | D4: 96 | E4: 36 | F4: =SUM(C4:E4) -> 229 | G4: =AVERAGE(C4:E4) -> 76.333333 | H4: =ROUND(G4,2) -> 76.33
A5: 4 | B5: Ravi | C5: 85 | D5: 32 | E5: 15 | F5: =SUM(C5:E5) -> 132 | G5: =AVERAGE(C5:E5) -> 44 | H5: =ROUND(G5,2) -> 44
A6: 5 | B6: Vasanth | C6: 65 | D6: 85 | E6: 74 | F6: =SUM(C6:E6) -> 224 | G6: =AVERAGE(C6:E6) -> 74.666667 | H6: =ROUND(G6,2) -> 74.67
A7: 6 | B7: Mahesh | C7: 45 | D7: 75 | E7: 85 | F7: =SUM(C7:E7) -> 205 | G7: =AVERAGE(C7:E7) -> 68.333333 | H7: =ROUND(G7,2) -> 68.33
A8: 7 | B8: Rajesh | C8: 96 | D8: 85 | E8: 36 | F8: =SUM(C8:E8) -> 217 | G8: =AVERAGE(C8:E8) -> 72.333333 | H8: =ROUND(G8,2) -> 72.33
A9: 8 | B9: Sanjeev | C9: 35 | D9: 58 | E9: 62 | F9: =SUM(C9:E9) -> 155 | G9: =AVERAGE(C9:E9) -> 51.666667 | H9: =ROUND(G9,2) -> 51.67
A10: 9 | B10: Vinod | C10: 25 | D10: 59 | E10: 35 | F10: =SUM(C10:E10) -> 119 | G10: =AVERAGE(C10:E10) -> 39.666667 | H10: =ROUND(G10,2) -> 39.67
A11: 10 | B11: Daya | C11: 16 | D11: 74 | E11: 85 | F11: =SUM(C11:E11) -> 175 | G11: =AVERAGE(C11:E11) -> 58.333333 | H11: =ROUND(G11,2) -> 58.33
B13: max | C13: =MAX(C2:C11) -> 97 | D13: =MAX(D2:D11) -> 96 | E13: =MAX(E2:E11) -> 85 | F13: =MAX(F2:F11) -> 229 | G13: =MAX(G2:G11) -> 76.333333
B14: min | C14: =MIN(C2:C11) -> 16 | D14: =MIN(D2:D11) -> 32 | E14: =MIN(E2:E11) -> 15 | F14: =MIN(F2:F11) -> 119 | G14: =MIN(G2:G11) -> 39.666667
C15: =COUNT(C2:C11) -> 10

Sheet Formula auditing 2
C1: Tax | D1: 0.18
A3: SL NO | B3: Product Name | C3: Price | D3: Tax amount | E3: Total
A4: 1 | B4: Nokia | C4: 4500 | D4: =C4*$D$1 -> 810 | E4: =C4+D4 -> 5310
A5: 2 | B5: Samsung | C5: 68500 | D5: =C5*$D$1 -> 12330
A6: 3 | B6: Micromax | C6: 4800 | D6: =C6*$D$1 -> 864
A7: 4 | B7: Lenova | C7: 8450 | D7: =C7*$D$1 -> 1521
A8: 5 | B8: Motorola | C8: 8450 | D8: =C8*$D$1 -> 1521
C10: =SUM(mobileprice) -> 94700 | D10: =SUM(D4:D8) -> 17046
B12: 10
D13: =$B12+$B14 -> 30 | E13: =$B12+$B14 -> 30 | G13: =$B$12+$B$14 -> 30
B14: 20 | D14: =$B13+$B15 -> 0
D15: =B12+B14 -> 30 | G15: =E12+E14 -> 0
D18: =$B$12+B$14 -> 30
D19: =$B$12+$B$14 -> 30 | G19: =$B$12+$B$14 -> 30
A21: =$B$12+$B$14 -> 30 | F21: =$B$24+$B$26 -> 30
B24: 10
D25: =B24+B26 -> 30 | E25: =C24+C26 -> 0
B26: 20
E29: =C28+C30 -> 0
B37: Laptops | F37: =Price*quantity -> 142500
B38: Price | C38: 28500
B39: Qty | C39: 5
C41: =C38*C39 -> 142500
A46: Salary | B46: 12500
A47: PF | B47: =B46*PF -> 1562.5
B52: 10
B53: 0
B55: =B52/B53 -> #DIV/0!

Sheet Formula auditing 3
A1: Emp Id | B1: Emp Name | C1: Designation | D1: City type | E1: Basic | F1: DA | G1: HRA | H1: TA | I1: Gross salary | J1: PF | K1: PT | L1: Insurance | M1: Deduction Total | N1: Net Salary
A2: E001 | B2: Naveen | C2: Manager | D2: A | E2: 18050 | F2: =E2*52% -> 9386 | G2: =IF(D2="A",E2*25%,IF(D2="B",E2*15%,E2*10%)) -> 4512.5 | H2: =E2*8% -> 1444 | I2: =SUM(E2:H2) -> 33392.5 | J2: =E2*12.5% -> 2256.25 | K2: =IF(I2<=10000,100,IF(AND(I2>10000,I2<=20000),200,300)) -> 300 | L2: 500
A3: E002 | B3: Vinay | C3: Sales Manager | D3: B | E3: 3500 | F3: =E3*52% -> 1820 | G3: =IF(D3="A",E3*25%,IF(D3="B",E3*15%,E3*10%)) -> 525 | H3: =E3*8% -> 280 | I3: =SUM(E3:H3) -> 6125 | J3: =E3*12.5% -> 437.5 | K3: =IF(I3<=10000,100,IF(AND(I3>10000,I3<=20000),200,300)) -> 100 | L3: 200
A4: E003 | B4: Rajesh | C4: Administrator | D4: A | E4: 7500 | F4: =E4*52% -> 3900 | G4: =IF(D4="A",E4*25%,IF(D4="B",E4*15%,E4*10%)) -> 1875 | H4: =E4*8% -> 600 | I4: =SUM(E4:H4) -> 13875 | J4: =E4*12.5% -> 937.5 | K4: =IF(I4<=10000,100,IF(AND(I4>10000,I4<=20000),200,300)) -> 200 | L4: 3500
A5: E004 | B5: Anand | C5: Trainer | D5: A | E5: 6500 | F5: =E5*52% -> 3380 | G5: =IF(D5="A",E5*25%,IF(D5="B",E5*15%,E5*10%)) -> 1625 | H5: =E5*8% -> 520 | I5: =SUM(E5:H5) -> 12025 | J5: =E5*12.5% -> 812.5 | K5: =IF(I5<=10000,100,IF(AND(I5>10000,I5<=20000),200,300)) -> 200 | L5: 2500
A6: E005 | B6: Mahendra | C6: Coordinator | D6: C | E6: 15000 | F6: =E6*52% -> 7800 | G6: =IF(D6="A",E6*25%,IF(D6="B",E6*15%,E6*10%)) -> 1500 | H6: =E6*8% -> 1200 | I6: =SUM(E6:H6) -> 25500 | J6: =E6*12.5% -> 1875 | K6: =IF(I6<=10000,100,IF(AND(I6>10000,I6<=20000),200,300)) -> 300 | L6: 2000
A7: E006 | B7: Kumar | C7: Clerk | D7: C | E7: 6500 | F7: =E7*52% -> 3380 | G7: =IF(D7="A",E7*25%,IF(D7="B",E7*15%,E7*10%)) -> 650 | H7: =E7*8% -> 520 | I7: =SUM(E7:H7) -> 11050 | J7: =E7*12.5% -> 812.5 | K7: =IF(I7<=10000,100,IF(AND(I7>10000,I7<=20000),200,300)) -> 200 | L7: 3200
A8: E007 | B8: Daya | C8: Trainer | D8: B | E8: 3500 | F8: =E8*52% -> 1820 | G8: =IF(D8="A",E8*25%,IF(D8="B",E8*15%,E8*10%)) -> 525 | H8: =E8*8% -> 280 | I8: =SUM(E8:H8) -> 6125 | J8: =E8*12.5% -> 437.5 | K8: =IF(I8<=10000,100,IF(AND(I8>10000,I8<=20000),200,300)) -> 100 | L8: 1500
A9: E008 | B9: Sanjana | C9: Manager | D9: A | E9: 4500 | F9: =E9*52% -> 2340 | G9: =IF(D9="A",E9*25%,IF(D9="B",E9*15%,E9*10%)) -> 1125 | H9: =E9*8% -> 360 | I9: =SUM(E9:H9) -> 8325 | J9: =E9*12.5% -> 562.5 | K9: =IF(I9<=10000,100,IF(AND(I9>10000,I9<=20000),200,300)) -> 100 | L9: 800
A10: E009 | B10: Pooja | C10: Sales rep | D10: B | E10: 7400 | F10: =E10*52% -> 3848 | G10: =IF(D10="A",E10*25%,IF(D10="B",E10*15%,E10*10%)) -> 1110 | H10: =E10*8% -> 592 | I10: =SUM(E10:H10) -> 12950 | J10: =E10*12.5% -> 925 | K10: =IF(I10<=10000,100,IF(AND(I10>10000,I10<=20000),200,300)) -> 200 | L10: 950
A11: E010 | B11: Mahesh | C11: Marketing Executive | D11: C | E11: 14200 | F11: =E11*52% -> 7384 | G11: =IF(D11="A",E11*25%,IF(D11="B",E11*15%,E11*10%)) -> 1420 | H11: =E11*8% -> 1136 | I11: =SUM(E11:H11) -> 24140 | J11: =E11*12.5% -> 1775 | K11: =IF(I11<=10000,100,IF(AND(I11>10000,I11<=20000),200,300)) -> 300 | L11: 1500
C14: DA | D14: 52% of basic
C15: HRA | D15: City type A, 25% of Basic City type B, 15% of Basic City type C, 10% of Basic
C16: TA | D16: 8% of Basic
C18: PF | D18: 12.5% of Basic
C19: PT | D19: Gross Salary <=10000,100 Gross Salary >10000 and <=20000 ,200 Gross Salary > 20000,300
Z86: 5
Y139: 5
E156: 5
A489: Emp Id | B489: Emp Name | C489: Designation
A490: E001 | B490: Naveen | C490: Manager
A491: E002 | B491: Vinay | C491: Sales Manager
A492: E003 | B492: Rajesh | C492: Administrator

Sheet Formula Auditing 4
A1: Employee ID | B1: Name | C1: TYPE | D1: DEPARTMENT
A2: A001 | B2: Vinaykumar | C2: Permanent | D2: =IFERROR(VLOOKUP(A2,[10]Sheet10!$A$1:$D$10,4,FALSE),"") -> Administration | E2: =VLOOKUP(A2,'Formula Auditing 5'!$A$1:$D$10,4,FALSE) -> Administration
A3: A002 | B3: Rajeev | C3: Temporary | D3: =IFERROR(VLOOKUP(A3,[10]Sheet10!$A$1:$D$10,4,FALSE),"") | E3: =VLOOKUP(A3,'Formula Auditing 5'!$A$1:$D$10,4,FALSE) -> #N/A
A4: A003 | B4: Prasad | C4: Contract | D4: =IFERROR(VLOOKUP(A4,[10]Sheet10!$A$1:$D$10,4,FALSE),"") -> Marketing | E4: =VLOOKUP(A4,'Formula Auditing 5'!$A$1:$D$10,4,FALSE) -> Marketing
A5: A004 | B5: Sunitha | C5: Contract | D5: =IFERROR(VLOOKUP(A5,[10]Sheet10!$A$1:$D$10,4,FALSE),"") -> Human Resource | E5: =VLOOKUP(A5,'Formula Auditing 5'!$A$1:$D$10,4,FALSE) -> Human Resource
A6: A005 | B6: Robert | C6: Temporary | D6: =IFERROR(VLOOKUP(A6,[10]Sheet10!$A$1:$D$10,4,FALSE),"") -> Training | E6: =VLOOKUP(A6,'Formula Auditing 5'!$A$1:$D$10,4,FALSE) -> Training
A7: A006 | B7: Daya | C7: Temporary | D7: =IFERROR(VLOOKUP(A7,[10]Sheet10!$A$1:$D$10,4,FALSE),"") | E7: =VLOOKUP(A7,'Formula Auditing 5'!$A$1:$D$10,4,FALSE) -> #N/A
A8: A007 | B8: Mahesh | C8: Contract | D8: =IFERROR(VLOOKUP(A8,[10]Sheet10!$A$1:$D$10,4,FALSE),"") -> Quality | E8: =VLOOKUP(A8,'Formula Auditing 5'!$A$1:$D$10,4,FALSE) -> Quality
A9: A008 | B9: Robin | C9: Temporary | D9: =IFERROR(VLOOKUP(A9,[10]Sheet10!$A$1:$D$10,4,FALSE),"") -> Administration | E9: =VLOOKUP(A9,'Formula Auditing 5'!$A$1:$D$10,4,FALSE) -> Administration
A10: A009 | B10: Venkatesh | C10: Contract | D10: =IFERROR(VLOOKUP(A10,[10]Sheet10!$A$1:$D$10,4,FALSE),"") -> Sales | E10: =VLOOKUP(A10,'Formula Auditing 5'!$A$1:$D$10,4,FALSE) -> Sales
A11: A010 | B11: Vivek | C11: Permanent | D11: =IFERROR(VLOOKUP(A11,[10]Sheet10!$A$1:$D$10,4,FALSE),"") -> Marketing | E11: =VLOOKUP(A11,'Formula Auditing 5'!$A$1:$D$10,4,FALSE) -> Marketing

Sheet Formula Auditing 5
A1: Employee ID | B1: Name | C1: TYPE | D1: DEPARTMENT
A2: A007 | B2: Mahesh | C2: Contract | D2: Quality
A3: A003 | B3: Prasad | C3: Contract | D3: Marketing
A4: A005 | B4: Robert | C4: Temporary | D4: Training
A5: A008 | B5: Robin | C5: Temporary | D5: Administration
A6: A004 | B6: Sunitha | C6: Contract | D6: Human Resource
A7: A012 | B7: Vasanth | C7: Temporary | D7: Marketing
A8: A009 | B8: Venkatesh | C8: Contract | D8: Sales
A9: A001 | B9: Vinaykumar | C9: Permanent | D9: Administration
A10: A010 | B10: Vivek | C10: Permanent | D10: Marketing
